Workbook

Sheet Resumen
A1: Resumen Orbiluz
A2: Se calcula solo. No escribas en esta hoja.
D3: Por producto
A4: Pedidos | B4: =COUNTA(Pedidos!A2:A301) | D4: Producto | E4: Unidades | F4: Ingresos (€) | G4: Beneficio (€)
A5: Pedidos cancelados o devueltos | B5: =COUNTIF(Pedidos!U2:U301,"Cancelado")+COUNTIF(Pedidos!U2:U301,"Devuelto") | D5: Lámpara bola de cristal 3D | E5: =SUMIF(Pedidos!$G$2:$G$301,D5,Pedidos!$I$2:$I$301) | F5: =SUMIF(Pedidos!$G$2:$G$301,D5,Pedidos!$M$2:$M$301) | G5: =SUMIF(Pedidos!$G$2:$G$301,D5,Pedidos!$R$2:$R$301)
A6: Ingresos cobrados con IVA (€) | B6: =SUM(Pedidos!M2:M301) | D6: Reloj LED 3D de pared y mesa | E6: =SUMIF(Pedidos!$G$2:$G$301,D6,Pedidos!$I$2:$I$301) | F6: =SUMIF(Pedidos!$G$2:$G$301,D6,Pedidos!$M$2:$M$301) | G6: =SUMIF(Pedidos!$G$2:$G$301,D6,Pedidos!$R$2:$R$301)
A7: Ingresos sin IVA (€) | B7: =B6/1.21 | D7: Proyector de ondas de agua | E7: =SUMIF(Pedidos!$G$2:$G$301,D7,Pedidos!$I$2:$I$301) | F7: =SUMIF(Pedidos!$G$2:$G$301,D7,Pedidos!$M$2:$M$301) | G7: =SUMIF(Pedidos!$G$2:$G$301,D7,Pedidos!$R$2:$R$301)
A8: Beneficio (€) | B8: =SUM(Pedidos!R2:R301) | D8: Globo terráqueo que levita | E8: =SUMIF(Pedidos!$G$2:$G$301,D8,Pedidos!$I$2:$I$301) | F8: =SUMIF(Pedidos!$G$2:$G$301,D8,Pedidos!$M$2:$M$301) | G8: =SUMIF(Pedidos!$G$2:$G$301,D8,Pedidos!$R$2:$R$301)
A9: Margen medio | B9: =IF(B7=0,"",B8/B7)
A10: Ticket medio (€) | B10: =IF(B4=0,"",B6/B4)
A11: Publicidad asignada (€) | B11: =SUM(Pedidos!Q2:Q301) | D11: Por origen
A12: ROAS (ingresos / publicidad) | B12: =IF(B11=0,"",B6/B11) | D12: Origen | E12: Pedidos | F12: Ingresos (€) | G12: Beneficio (€)
A13: Clientes | B13: =COUNTA(Clientes!A2:A301) | D13: Meta Ads | E13: =COUNTIF(Pedidos!$T$2:$T$301,D13) | F13: =SUMIF(Pedidos!$T$2:$T$301,D13,Pedidos!$M$2:$M$301) | G13: =SUMIF(Pedidos!$T$2:$T$301,D13,Pedidos!$R$2:$R$301)
A14: Clientes que repiten | B14: =COUNTIF(Clientes!F2:F301,">1") | D14: TikTok Ads | E14: =COUNTIF(Pedidos!$T$2:$T$301,D14) | F14: =SUMIF(Pedidos!$T$2:$T$301,D14,Pedidos!$M$2:$M$301) | G14: =SUMIF(Pedidos!$T$2:$T$301,D14,Pedidos!$R$2:$R$301)
A15: Carritos abandonados | B15: =COUNTA('Carritos abandonados'!B2:B301) | D15: Instagram orgánico | E15: =COUNTIF(Pedidos!$T$2:$T$301,D15) | F15: =SUMIF(Pedidos!$T$2:$T$301,D15,Pedidos!$M$2:$M$301) | G15: =SUMIF(Pedidos!$T$2:$T$301,D15,Pedidos!$R$2:$R$301)
A16: Carritos recuperados | B16: =COUNTIF('Carritos abandonados'!K2:K301,"Sí") | D16: TikTok orgánico | E16: =COUNTIF(Pedidos!$T$2:$T$301,D16) | F16: =SUMIF(Pedidos!$T$2:$T$301,D16,Pedidos!$M$2:$M$301) | G16: =SUMIF(Pedidos!$T$2:$T$301,D16,Pedidos!$R$2:$R$301)
A17: Tasa de recuperación | B17: =IF(B15=0,"",B16/B15) | D17: Google | E17: =COUNTIF(Pedidos!$T$2:$T$301,D17) | F17: =SUMIF(Pedidos!$T$2:$T$301,D17,Pedidos!$M$2:$M$301) | G17: =SUMIF(Pedidos!$T$2:$T$301,D17,Pedidos!$R$2:$R$301)
A18: Devoluciones | B18: =COUNTA(Devoluciones!A2:A301) | D18: Directo | E18: =COUNTIF(Pedidos!$T$2:$T$301,D18) | F18: =SUMIF(Pedidos!$T$2:$T$301,D18,Pedidos!$M$2:$M$301) | G18: =SUMIF(Pedidos!$T$2:$T$301,D18,Pedidos!$R$2:$R$301)
A19: Tasa de devolución | B19: =IF(B4=0,"",B18/B4) | D19: Carrito recuperado | E19: =COUNTIF(Pedidos!$T$2:$T$301,D19) | F19: =SUMIF(Pedidos!$T$2:$T$301,D19,Pedidos!$M$2:$M$301) | G19: =SUMIF(Pedidos!$T$2:$T$301,D19,Pedidos!$R$2:$R$301)
D20: Otro | E20: =COUNTIF(Pedidos!$T$2:$T$301,D20) | F20: =SUMIF(Pedidos!$T$2:$T$301,D20,Pedidos!$M$2:$M$301) | G20: =SUMIF(Pedidos!$T$2:$T$301,D20,Pedidos!$R$2:$R$301)

Sheet Cómo usarlo
A1: Cómo usar este registro
A3: 1. Rellena primero la hoja Parámetros: el coste de cada producto y la comisión de pago (celdas amarillas).
A4: 2. Cada venta = una fila en Pedidos (si un pedido lleva 2 productos distintos, usa 2 filas con el mismo Nº de pedido).
A5: 3. Escribe solo en las columnas de texto azul. Las negras y verdes se calculan solas.
A6: 4. Añade al cliente en Clientes con el mismo email: el nº de pedidos y lo gastado se suman solos.
A7: 5. Carritos abandonados: apunta los de Shopify › Pedidos › Carritos abandonados y marca si se recuperan.
A8: 6. Devoluciones: el plazo de 14 días se comprueba solo a partir de la fecha de entrega del pedido.
A9: 7. La fila 2 de Pedidos es un EJEMPLO: bórrala antes de empezar.
A11: Protección de datos (RGPD)
A12: Este archivo contiene datos personales. Guarda la copia rellena en gestion/datos/ (está excluida de Git) o en tu ordenador,
A13: nunca en un repositorio ni en una carpeta compartida. Borra los datos de quien lo pida y no los guardes más tiempo del necesario.
A15: Colores: azul = lo escribes tú · negro = fórmula · verde = viene de otra hoja · amarillo = dato que falta.

Sheet Parámetros
A1: Parámetros (rellena lo amarillo)
A3: Comisión de pago (%) | B3: 0.019 | C3: Confírmalo en Shopify › Configuración › Pagos: depende de tu plan y del tipo de tarjeta.
A4: Comisión de pago fija por pedido (€) | B4: 0.25
A6: Productos
A7: Producto | B7: Precio de venta (€) | C7: Coste proveedor por unidad (€) | D7: Coste envío proveedor por unidad (€) | E7: Coste real del proveedor (en USD: pásalo a euros al cambio del día)
A8: Lámpara bola de cristal 3D | B8: 24.9 | E8: DSers 29/09/2026: 7,59-7,85 USD + envío 1,99 USD (AliExpress Selection Premium, 5-9 días)
A9: Reloj LED 3D de pared y mesa | B9: 29.9 | E9: DSers 29/09/2026: 7,51-8,62 USD + envío 1,99 USD (AliExpress Selection Premium, 5-9 días)
A10: Proyector de ondas de agua | B10: 29.9 | E10: DSers 29/09/2026: 11,18 USD + envío 1,99 USD (AliExpress Selection Premium, 5-9 días)
A11: Globo terráqueo que levita | B11: 129 | E11: DSers 29/09/2026: 47,43 USD + envío 27,58 USD (1688, envío especial, 10-15 días)

Sheet Pedidos
A1: Nº pedido | B1: Fecha | C1: Nombre cliente | D1: Email | E1: Teléfono | F1: Provincia | G1: Producto | H1: Variante | I1: Unidades | J1: Precio unidad (€) | K1: Descuento (€) | L1: Envío cobrado (€) | M1: Total cobrado (€) | N1: Coste producto (€) | O1: Coste envío proveedor (€) | P1: Comisión pago (€) | Q1: Publicidad asignada (€) | R1: Beneficio (€) | S1: Margen | T1: Origen | U1: Estado | V1: Pedido proveedor (DSers) | W1: Nº seguimiento | X1: Fecha envío | Y1: Fecha entrega | Z1: Notas
A2: EJEMPLO-1001 | B2: 46296 | C2: Cliente Ejemplo | D2: ejemplo@correo.com | E2: 600000000 | F2: Granada | G2: Lámpara bola de cristal 3D | H2: Saturno | I2: 2 | J2: =IF(G2="","",IFERROR(INDEX(Parámetros!$B$8:$B$20,MATCH(G2,Parámetros!$A$8:$A$20,0)),"")) | K2: 9.9 | L2: 0 | M2: =IF(A2="","",I2*J2-K2+L2) | N2: =IF(A2="","",IFERROR(I2*INDEX(Parámetros!$C$8:$C$20,MATCH(G2,Parámetros!$A$8:$A$20,0)),0)) | O2: =IF(A2="","",IFERROR(I2*INDEX(Parámetros!$D$8:$D$20,MATCH(G2,Parámetros!$A$8:$A$20,0)),0)) | P2: =IF(A2="","",M2*Parámetros!$B$3+Parámetros!$B$4) | Q2: 6 | R2: =IF(A2="","",M2/1.21-N2-O2-P2-Q2) | S2: =IF(OR(A2="",M2=0),"",R2/(M2/1.21)) | T2: Meta Ads | U2: Enviado | V2: DS-000000 | W2: (nº de seguimiento) | X2: 46297 | Z2: Fila de ejemplo: 2 lámparas con la promo 2×39,90 €. Bórrala.
J3: =IF(G3="","",IFERROR(INDEX(Parámetros!$B$8:$B$20,MATCH(G3,Parámetros!$A$8:$A$20,0)),"")) | M3: =IF(A3="","",I3*J3-K3+L3) | N3: =IF(A3="","",IFERROR(I3*INDEX(Parámetros!$C$8:$C$20,MATCH(G3,Parámetros!$A$8:$A$20,0)),0)) | O3: =IF(A3="","",IFERROR(I3*INDEX(Parámetros!$D$8:$D$20,MATCH(G3,Parámetros!$A$8:$A$20,0)),0)) | P3: =IF(A3="","",M3*Parámetros!$B$3+Parámetros!$B$4) | R3: =IF(A3="","",M3/1.21-N3-O3-P3-Q3) | S3: =IF(OR(A3="",M3=0),"",R3/(M3/1.21))
J4: =IF(G4="","",IFERROR(INDEX(Parámetros!$B$8:$B$20,MATCH(G4,Parámetros!$A$8:$A$20,0)),"")) | M4: =IF(A4="","",I4*J4-K4+L4) | N4: =IF(A4="","",IFERROR(I4*INDEX(Parámetros!$C$8:$C$20,MATCH(G4,Parámetros!$A$8:$A$20,0)),0)) | O4: =IF(A4="","",IFERROR(I4*INDEX(Parámetros!$D$8:$D$20,MATCH(G4,Parámetros!$A$8:$A$20,0)),0)) | P4: =IF(A4="","",M4*Parámetros!$B$3+Parámetros!$B$4) | R4: =IF(A4="","",M4/1.21-N4-O4-P4-Q4) | S4: =IF(OR(A4="",M4=0),"",R4/(M4/1.21))
J5: =IF(G5="","",IFERROR(INDEX(Parámetros!$B$8:$B$20,MATCH(G5,Parámetros!$A$8:$A$20,0)),"")) | M5: =IF(A5="","",I5*J5-K5+L5) | N5: =IF(A5="","",IFERROR(I5*INDEX(Parámetros!$C$8:$C$20,MATCH(G5,Parámetros!$A$8:$A$20,0)),0)) | O5: =IF(A5="","",IFERROR(I5*INDEX(Parámetros!$D$8:$D$20,MATCH(G5,Parámetros!$A$8:$A$20,0)),0)) | P5: =IF(A5="","",M5*Parámetros!$B$3+Parámetros!$B$4) | R5: =IF(A5="","",M5/1.21-N5-O5-P5-Q5) | S5: =IF(OR(A5="",M5=0),"",R5/(M5/1.21))
J6: =IF(G6="","",IFERROR(INDEX(Parámetros!$B$8:$B$20,MATCH(G6,Parámetros!$A$8:$A$20,0)),"")) | M6: =IF(A6="","",I6*J6-K6+L6) | N6: =IF(A6="","",IFERROR(I6*INDEX(Parámetros!$C$8:$C$20,MATCH(G6,Parámetros!$A$8:$A$20,0)),0)) | O6: =IF(A6="","",IFERROR(I6*INDEX(Parámetros!$D$8:$D$20,MATCH(G6,Parámetros!$A$8:$A$20,0)),0)) | P6: =IF(A6="","",M6*Parámetros!$B$3+Parámetros!$B$4) | R6: =IF(A6="","",M6/1.21-N6-O6-P6-Q6) | S6: =IF(OR(A6="",M6=0),"",R6/(M6/1.21))
J7: =IF(G7="","",IFERROR(INDEX(Parámetros!$B$8:$B$20,MATCH(G7,Parámetros!$A$8:$A$20,0)),"")) | M7: =IF(A7="","",I7*J7-K7+L7) | N7: =IF(A7="","",IFERROR(I7*INDEX(Parámetros!$C$8:$C$20,MATCH(G7,Parámetros!$A$8:$A$20,0)),0)) | O7: =IF(A7="","",IFERROR(I7*INDEX(Parámetros!$D$8:$D$20,MATCH(G7,Parámetros!$A$8:$A$20,0)),0)) | P7: =IF(A7="","",M7*Parámetros!$B$3+Parámetros!$B$4) | R7: =IF(A7="","",M7/1.21-N7-O7-P7-Q7) | S7: =IF(OR(A7="",M7=0),"",R7/(M7/1.21))
J8: =IF(G8="","",IFERROR(INDEX(Parámetros!$B$8:$B$20,MATCH(G8,Parámetros!$A$8:$A$20,0)),"")) | M8: =IF(A8="","",I8*J8-K8+L8) | N8: =IF(A8="","",IFERROR(I8*INDEX(Parámetros!$C$8:$C$20,MATCH(G8,Parámetros!$A$8:$A$20,0)),0)) | O8: =IF(A8="","",IFERROR(I8*INDEX(Parámetros!$D$8:$D$20,MATCH(G8,Parámetros!$A$8:$A$20,0)),0)) | P8: =IF(A8="","",M8*Parámetros!$B$3+Parámetros!$B$4) | R8: =IF(A8="","",M8/1.21-N8-O8-P8-Q8) | S8: =IF(OR(A8="",M8=0),"",R8/(M8/1.21))
J9: =IF(G9="","",IFERROR(INDEX(Parámetros!$B$8:$B$20,MATCH(G9,Parámetros!$A$8:$A$20,0)),"")) | M9: =IF(A9="","",I9*J9-K9+L9) | N9: =IF(A9="","",IFERROR(I9*INDEX(Parámetros!$C$8:$C$20,MATCH(G9,Parámetros!$A$8:$A$20,0)),0)) | O9: =IF(A9="","",IFERROR(I9*INDEX(Parámetros!$D$8:$D$20,MATCH(G9,Parámetros!$A$8:$A$20,0)),0)) | P9: =IF(A9="","",M9*Parámetros!$B$3+Parámetros!$B$4) | R9: =IF(A9="","",M9/1.21-N9-O9-P9-Q9) | S9: =IF(OR(A9="",M9=0),"",R9/(M9/1.21))
J10: =IF(G10="","",IFERROR(INDEX(Parámetros!$B$8:$B$20,MATCH(G10,Parámetros!$A$8:$A$20,0)),"")) | M10: =IF(A10="","",I10*J10-K10+L10) | N10: =IF(A10="","",IFERROR(I10*INDEX(Parámetros!$C$8:$C$20,MATCH(G10,Parámetros!$A$8:$A$20,0)),0)) | O10: =IF(A10="","",IFERROR(I10*INDEX(Parámetros!$D$8:$D$20,MATCH(G10,Parámetros!$A$8:$A$20,0)),0)) | P10: =IF(A10="","",M10*Parámetros!$B$3+Parámetros!$B$4) | R10: =IF(A10="","",M10/1.21-N10-O10-P10-Q10) | S10: =IF(OR(A10="",M10=0),"",R10/(M10/1.21))
J11: =IF(G11="","",IFERROR(INDEX(Parámetros!$B$8:$B$20,MATCH(G11,Parámetros!$A$8:$A$20,0)),"")) | M11: =IF(A11="","",I11*J11-K11+L11) | N11: =IF(A11="","",IFERROR(I11*INDEX(Parámetros!$C$8:$C$20,MATCH(G11,Parámetros!$A$8:$A$20,0)),0)) | O11: =IF(A11="","",IFERROR(I11*INDEX(Parámetros!$D$8:$D$20,MATCH(G11,Parámetros!$A$8:$A$20,0)),0)) | P11: =IF(A11="","",M11*Parámetros!$B$3+Parámetros!$B$4) | R11: =IF(A11="","",M11/1.21-N11-O11-P11-Q11) | S11: =IF(OR(A11="",M11=0),"",R11/(M11/1.21))
J12: =IF(G12="","",IFERROR(INDEX(Parámetros!$B$8:$B$20,MATCH(G12,Parámetros!$A$8:$A$20,0)),"")) | M12: =IF(A12="","",I12*J12-K12+L12) | N12: =IF(A12="","",IFERROR(I12*INDEX(Parámetros!$C$8:$C$20,MATCH(G12,Parámetros!$A$8:$A$20,0)),0)) | O12: =IF(A12="","",IFERROR(I12*INDEX(Parámetros!$D$8:$D$20,MATCH(G12,Parámetros!$A$8:$A$20,0)),0)) | P12: =IF(A12="","",M12*Parámetros!$B$3+Parámetros!$B$4) | R12: =IF(A12="","",M12/1.21-N12-O12-P12-Q12) | S12: =IF(OR(A12="",M12=0),"",R12/(M12/1.21))
J13: =IF(G13="","",IFERROR(INDEX(Parámetros!$B$8:$B$20,MATCH(G13,Parámetros!$A$8:$A$20,0)),"")) | M13: =IF(A13="","",I13*J13-K13+L13) | N13: =IF(A13="","",IFERROR(I13*INDEX(Parámetros!$C$8:$C$20,MATCH(G13,Parámetros!$A$8:$A$20,0)),0)) | O13: =IF(A13="","",IFERROR(I13*INDEX(Parámetros!$D$8:$D$20,MATCH(G13,Parámetros!$A$8:$A$20,0)),0)) | P13: =IF(A13="","",M13*Parámetros!$B$3+Parámetros!$B$4) | R13: =IF(A13="","",M13/1.21-N13-O13-P13-Q13) | S13: =IF(OR(A13="",M13=0),"",R13/(M13/1.21))
J14: =IF(G14="","",IFERROR(INDEX(Parámetros!$B$8:$B$20,MATCH(G14,Parámetros!$A$8:$A$20,0)),"")) | M14: =IF(A14="","",I14*J14-K14+L14) | N14: =IF(A14="","",IFERROR(I14*INDEX(Parámetros!$C$8:$C$20,MATCH(G14,Parámetros!$A$8:$A$20,0)),0)) | O14: =IF(A14="","",IFERROR(I14*INDEX(Parámetros!$D$8:$D$20,MATCH(G14,Parámetros!$A$8:$A$20,0)),0)) | P14: =IF(A14="","",M14*Parámetros!$B$3+Parámetros!$B$4) | R14: =IF(A14="","",M14/1.21-N14-O14-P14-Q14) | S14: =IF(OR(A14="",M14=0),"",R14/(M14/1.21))
... J301: =IF(G301="","",IFERROR(INDEX(Parámetros!$B$8:$B$20,MATCH(G301,Parámetros!$A$8:$A$20,0)),"")) | M301: =IF(A301="","",I301*J301-K301+L301) | N301: =IF(A301="","",IFERROR(I301*INDEX(Parámetros!$C$8:$C$20,MATCH(G301,Parámetros!$A$8:$A$20,0)),0)) | O301: =IF(A301="","",IFERROR(I301*INDEX(Parámetros!$D$8:$D$20,MATCH(G301,Parámetros!$A$8:$A$20,0)),0)) | P301: =IF(A301="","",M301*Parámetros!$B$3+Parámetros!$B$4) | R301: =IF(A301="","",M301/1.21-N301-O301-P301-Q301) | S301: =IF(OR(A301="",M301=0),"",R301/(M301/1.21))

Sheet Clientes
A1: Email | B1: Nombre | C1: Teléfono | D1: Provincia | E1: Acepta marketing | F1: Nº pedidos | G1: Total gastado (€) | H1: Primer pedido | I1: Último pedido | J1: Notas
F2: =IF(A2="","",COUNTIF(Pedidos!$D$2:$D$301,A2)) | G2: =IF(A2="","",SUMIF(Pedidos!$D$2:$D$301,A2,Pedidos!$M$2:$M$301)) | H2: =IF(OR(A2="",F2=0),"",_xlfn.MINIFS(Pedidos!$B$2:$B$301,Pedidos!$D$2:$D$301,A2)) | I2: =IF(OR(A2="",F2=0),"",_xlfn.MAXIFS(Pedidos!$B$2:$B$301,Pedidos!$D$2:$D$301,A2))
F3: =IF(A3="","",COUNTIF(Pedidos!$D$2:$D$301,A3)) | G3: =IF(A3="","",SUMIF(Pedidos!$D$2:$D$301,A3,Pedidos!$M$2:$M$301)) | H3: =IF(OR(A3="",F3=0),"",_xlfn.MINIFS(Pedidos!$B$2:$B$301,Pedidos!$D$2:$D$301,A3)) | I3: =IF(OR(A3="",F3=0),"",_xlfn.MAXIFS(Pedidos!$B$2:$B$301,Pedidos!$D$2:$D$301,A3))
F4: =IF(A4="","",COUNTIF(Pedidos!$D$2:$D$301,A4)) | G4: =IF(A4="","",SUMIF(Pedidos!$D$2:$D$301,A4,Pedidos!$M$2:$M$301)) | H4: =IF(OR(A4="",F4=0),"",_xlfn.MINIFS(Pedidos!$B$2:$B$301,Pedidos!$D$2:$D$301,A4)) | I4: =IF(OR(A4="",F4=0),"",_xlfn.MAXIFS(Pedidos!$B$2:$B$301,Pedidos!$D$2:$D$301,A4))
F5: =IF(A5="","",COUNTIF(Pedidos!$D$2:$D$301,A5)) | G5: =IF(A5="","",SUMIF(Pedidos!$D$2:$D$301,A5,Pedidos!$M$2:$M$301)) | H5: =IF(OR(A5="",F5=0),"",_xlfn.MINIFS(Pedidos!$B$2:$B$301,Pedidos!$D$2:$D$301,A5)) | I5: =IF(OR(A5="",F5=0),"",_xlfn.MAXIFS(Pedidos!$B$2:$B$301,Pedidos!$D$2:$D$301,A5))
F6: =IF(A6="","",COUNTIF(Pedidos!$D$2:$D$301,A6)) | G6: =IF(A6="","",SUMIF(Pedidos!$D$2:$D$301,A6,Pedidos!$M$2:$M$301)) | H6: =IF(OR(A6="",F6=0),"",_xlfn.MINIFS(Pedidos!$B$2:$B$301,Pedidos!$D$2:$D$301,A6)) | I6: =IF(OR(A6="",F6=0),"",_xlfn.MAXIFS(Pedidos!$B$2:$B$301,Pedidos!$D$2:$D$301,A6))
F7: =IF(A7="","",COUNTIF(Pedidos!$D$2:$D$301,A7)) | G7: =IF(A7="","",SUMIF(Pedidos!$D$2:$D$301,A7,Pedidos!$M$2:$M$301)) | H7: =IF(OR(A7="",F7=0),"",_xlfn.MINIFS(Pedidos!$B$2:$B$301,Pedidos!$D$2:$D$301,A7)) | I7: =IF(OR(A7="",F7=0),"",_xlfn.MAXIFS(Pedidos!$B$2:$B$301,Pedidos!$D$2:$D$301,A7))
F8: =IF(A8="","",COUNTIF(Pedidos!$D$2:$D$301,A8)) | G8: =IF(A8="","",SUMIF(Pedidos!$D$2:$D$301,A8,Pedidos!$M$2:$M$301)) | H8: =IF(OR(A8="",F8=0),"",_xlfn.MINIFS(Pedidos!$B$2:$B$301,Pedidos!$D$2:$D$301,A8)) | I8: =IF(OR(A8="",F8=0),"",_xlfn.MAXIFS(Pedidos!$B$2:$B$301,Pedidos!$D$2:$D$301,A8))
F9: =IF(A9="","",COUNTIF(Pedidos!$D$2:$D$301,A9)) | G9: =IF(A9="","",SUMIF(Pedidos!$D$2:$D$301,A9,Pedidos!$M$2:$M$301)) | H9: =IF(OR(A9="",F9=0),"",_xlfn.MINIFS(Pedidos!$B$2:$B$301,Pedidos!$D$2:$D$301,A9)) | I9: =IF(OR(A9="",F9=0),"",_xlfn.MAXIFS(Pedidos!$B$2:$B$301,Pedidos!$D$2:$D$301,A9))
F10: =IF(A10="","",COUNTIF(Pedidos!$D$2:$D$301,A10)) | G10: =IF(A10="","",SUMIF(Pedidos!$D$2:$D$301,A10,Pedidos!$M$2:$M$301)) | H10: =IF(OR(A10="",F10=0),"",_xlfn.MINIFS(Pedidos!$B$2:$B$301,Pedidos!$D$2:$D$301,A10)) | I10: =IF(OR(A10="",F10=0),"",_xlfn.MAXIFS(Pedidos!$B$2:$B$301,Pedidos!$D$2:$D$301,A10))
F11: =IF(A11="","",COUNTIF(Pedidos!$D$2:$D$301,A11)) | G11: =IF(A11="","",SUMIF(Pedidos!$D$2:$D$301,A11,Pedidos!$M$2:$M$301)) | H11: =IF(OR(A11="",F11=0),"",_xlfn.MINIFS(Pedidos!$B$2:$B$301,Pedidos!$D$2:$D$301,A11)) | I11: =IF(OR(A11="",F11=0),"",_xlfn.MAXIFS(Pedidos!$B$2:$B$301,Pedidos!$D$2:$D$301,A11))
F12: =IF(A12="","",COUNTIF(Pedidos!$D$2:$D$301,A12)) | G12: =IF(A12="","",SUMIF(Pedidos!$D$2:$D$301,A12,Pedidos!$M$2:$M$301)) | H12: =IF(OR(A12="",F12=0),"",_xlfn.MINIFS(Pedidos!$B$2:$B$301,Pedidos!$D$2:$D$301,A12)) | I12: =IF(OR(A12="",F12=0),"",_xlfn.MAXIFS(Pedidos!$B$2:$B$301,Pedidos!$D$2:$D$301,A12))
F13: =IF(A13="","",COUNTIF(Pedidos!$D$2:$D$301,A13)) | G13: =IF(A13="","",SUMIF(Pedidos!$D$2:$D$301,A13,Pedidos!$M$2:$M$301)) | H13: =IF(OR(A13="",F13=0),"",_xlfn.MINIFS(Pedidos!$B$2:$B$301,Pedidos!$D$2:$D$301,A13)) | I13: =IF(OR(A13="",F13=0),"",_xlfn.MAXIFS(Pedidos!$B$2:$B$301,Pedidos!$D$2:$D$301,A13))
... F301: =IF(A301="","",COUNTIF(Pedidos!$D$2:$D$301,A301)) | G301: =IF(A301="","",SUMIF(Pedidos!$D$2:$D$301,A301,Pedidos!$M$2:$M$301)) | H301: =IF(OR(A301="",F301=0),"",_xlfn.MINIFS(Pedidos!$B$2:$B$301,Pedidos!$D$2:$D$301,A301)) | I301: =IF(OR(A301="",F301=0),"",_xlfn.MAXIFS(Pedidos!$B$2:$B$301,Pedidos!$D$2:$D$301,A301))

Sheet Carritos abandonados
A1: Fecha | B1: Email | C1: Nombre | D1: Productos | E1: Importe (€) | F1: Acepta marketing | G1: Email 1 (1 h) | H1: Email 2 (24 h) | I1: Email 3 (48 h) | J1: Código ofrecido | K1: Recuperado | L1: Nº pedido recuperado | M1: Notas

Sheet Devoluciones
A1: Nº pedido | B1: Fecha entrega | C1: Fecha solicitud | D1: Días desde entrega | E1: Dentro de plazo (14 días) | F1: Motivo | G1: Estado | H1: Importe reembolsado (€) | I1: Coste devolución (€) | J1: Notas
B2: =IF(A2="","",IFERROR(INDEX(Pedidos!$Y$2:$Y$301,MATCH(A2,Pedidos!$A$2:$A$301,0)),"")) | D2: =IF(OR(B2="",C2="",B2=0),"",C2-B2) | E2: =IF(D2="","",IF(D2<=14,"Sí","No"))
B3: =IF(A3="","",IFERROR(INDEX(Pedidos!$Y$2:$Y$301,MATCH(A3,Pedidos!$A$2:$A$301,0)),"")) | D3: =IF(OR(B3="",C3="",B3=0),"",C3-B3) | E3: =IF(D3="","",IF(D3<=14,"Sí","No"))
B4: =IF(A4="","",IFERROR(INDEX(Pedidos!$Y$2:$Y$301,MATCH(A4,Pedidos!$A$2:$A$301,0)),"")) | D4: =IF(OR(B4="",C4="",B4=0),"",C4-B4) | E4: =IF(D4="","",IF(D4<=14,"Sí","No"))
B5: =IF(A5="","",IFERROR(INDEX(Pedidos!$Y$2:$Y$301,MATCH(A5,Pedidos!$A$2:$A$301,0)),"")) | D5: =IF(OR(B5="",C5="",B5=0),"",C5-B5) | E5: =IF(D5="","",IF(D5<=14,"Sí","No"))
B6: =IF(A6="","",IFERROR(INDEX(Pedidos!$Y$2:$Y$301,MATCH(A6,Pedidos!$A$2:$A$301,0)),"")) | D6: =IF(OR(B6="",C6="",B6=0),"",C6-B6) | E6: =IF(D6="","",IF(D6<=14,"Sí","No"))
B7: =IF(A7="","",IFERROR(INDEX(Pedidos!$Y$2:$Y$301,MATCH(A7,Pedidos!$A$2:$A$301,0)),"")) | D7: =IF(OR(B7="",C7="",B7=0),"",C7-B7) | E7: =IF(D7="","",IF(D7<=14,"Sí","No"))
B8: =IF(A8="","",IFERROR(INDEX(Pedidos!$Y$2:$Y$301,MATCH(A8,Pedidos!$A$2:$A$301,0)),"")) | D8: =IF(OR(B8="",C8="",B8=0),"",C8-B8) | E8: =IF(D8="","",IF(D8<=14,"Sí","No"))
B9: =IF(A9="","",IFERROR(INDEX(Pedidos!$Y$2:$Y$301,MATCH(A9,Pedidos!$A$2:$A$301,0)),"")) | D9: =IF(OR(B9="",C9="",B9=0),"",C9-B9) | E9: =IF(D9="","",IF(D9<=14,"Sí","No"))
B10: =IF(A10="","",IFERROR(INDEX(Pedidos!$Y$2:$Y$301,MATCH(A10,Pedidos!$A$2:$A$301,0)),"")) | D10: =IF(OR(B10="",C10="",B10=0),"",C10-B10) | E10: =IF(D10="","",IF(D10<=14,"Sí","No"))
B11: =IF(A11="","",IFERROR(INDEX(Pedidos!$Y$2:$Y$301,MATCH(A11,Pedidos!$A$2:$A$301,0)),"")) | D11: =IF(OR(B11="",C11="",B11=0),"",C11-B11) | E11: =IF(D11="","",IF(D11<=14,"Sí","No"))
B12: =IF(A12="","",IFERROR(INDEX(Pedidos!$Y$2:$Y$301,MATCH(A12,Pedidos!$A$2:$A$301,0)),"")) | D12: =IF(OR(B12="",C12="",B12=0),"",C12-B12) | E12: =IF(D12="","",IF(D12<=14,"Sí","No"))
B13: =IF(A13="","",IFERROR(INDEX(Pedidos!$Y$2:$Y$301,MATCH(A13,Pedidos!$A$2:$A$301,0)),"")) | D13: =IF(OR(B13="",C13="",B13=0),"",C13-B13) | E13: =IF(D13="","",IF(D13<=14,"Sí","No"))
... B301: =IF(A301="","",IFERROR(INDEX(Pedidos!$Y$2:$Y$301,MATCH(A301,Pedidos!$A$2:$A$301,0)),"")) | D301: =IF(OR(B301="",C301="",B301=0),"",C301-B301) | E301: =IF(D301="","",IF(D301<=14,"Sí","No"))
